sqlit/__init__.py
sqlit/_version.py
sqlit/cli.py
sqlit/mock_settings.py
sqlit/core/__init__.py
sqlit/core/action_validation.py
sqlit/core/binding_contexts.py
sqlit/core/connection_manager.py
sqlit/core/input_context.py
sqlit/core/key_router.py
sqlit/core/keymap.py
sqlit/core/leader_commands.py
sqlit/core/state_base.py
sqlit/core/vim.py
sqlit/domains/__init__.py
sqlit/domains/connections/__init__.py
sqlit/domains/connections/app/__init__.py
sqlit/domains/connections/app/cloud_actions.py
sqlit/domains/connections/app/connection_flow.py
sqlit/domains/connections/app/credentials.py
sqlit/domains/connections/app/executor.py
sqlit/domains/connections/app/install_strategy.py
sqlit/domains/connections/app/installer.py
sqlit/domains/connections/app/mock_adapter_core.py
sqlit/domains/connections/app/mock_data.py
sqlit/domains/connections/app/mock_default_adapters.py
sqlit/domains/connections/app/mock_profiles.py
sqlit/domains/connections/app/mock_provider.py
sqlit/domains/connections/app/mock_settings.py
sqlit/domains/connections/app/mocks.py
sqlit/domains/connections/app/persist_utils.py
sqlit/domains/connections/app/save_connection.py
sqlit/domains/connections/app/session.py
sqlit/domains/connections/app/tunnel.py
sqlit/domains/connections/app/url_parser.py
sqlit/domains/connections/cli/__init__.py
sqlit/domains/connections/cli/commands.py
sqlit/domains/connections/cli/helpers.py
sqlit/domains/connections/cli/prompts.py
sqlit/domains/connections/discovery/__init__.py
sqlit/domains/connections/discovery/docker_detector.py
sqlit/domains/connections/discovery/cloud/__init__.py
sqlit/domains/connections/discovery/cloud/base.py
sqlit/domains/connections/discovery/cloud/mock.py
sqlit/domains/connections/discovery/cloud/registry.py
sqlit/domains/connections/discovery/cloud/aws/__init__.py
sqlit/domains/connections/discovery/cloud/aws/cache.py
sqlit/domains/connections/discovery/cloud/aws/provider.py
sqlit/domains/connections/discovery/cloud/azure/__init__.py
sqlit_tui-1.3.1.dist-info/METADATA
sqlit_tui-1.3.1.dist-info/WHEEL
sqlit_tui-1.3.1.dist-info/entry_points.txt
sqlit_tui-1.3.1.dist-info/licenses/LICENSE
sqlit_tui-1.3.1.dist-info/RECORD
