Metadata-Version: 2.4
Name: sqlit-tui
Version: 1.3.1
Summary: A terminal UI for SQL Server, PostgreSQL, MySQL, SQLite, Oracle, and more
Project-URL: Homepage, https://github.com/Maxteabag/sqlit
Project-URL: Repository, https://github.com/Maxteabag/sqlit
Project-URL: Issues, https://github.com/Maxteabag/sqlit/issues
Author: Peter
License-Expression: MIT
License-File: LICENSE
Keywords: database,firebird,mssql,mysql,oracle,postgresql,server,sql,sqlite,terminal,tui
Classifier: Development Status :: 4 - Beta
Classifier: Environment :: Console
Classifier: Intended Audience :: Developers
Classifier: License :: OSI Approved :: MIT License
Classifier: Operating System :: OS Independent
Classifier: Programming Language :: Python :: 3
Classifier: Programming Language :: Python :: 3.10
Classifier: Programming Language :: Python :: 3.11
Classifier: Programming Language :: Python :: 3.12
Classifier: Programming Language :: Python :: 3.13
Classifier: Topic :: Database
Requires-Python: >=3.10
Requires-Dist: docker>=7.0.0
Requires-Dist: keyring>=24.0.0
Requires-Dist: pyperclip>=1.8.2
Requires-Dist: sqlparse>=0.5.0
Requires-Dist: textual-fastdatatable>=0.14.0
Requires-Dist: textual[syntax]>=6.10.0
Provides-Extra: all
Requires-Dist: adbc-driver-flightsql>=1.0.0; extra == 'all'
Requires-Dist: clickhouse-connect>=0.7.0; extra == 'all'
Requires-Dist: duckdb>=1.1.0; extra == 'all'
Requires-Dist: firebirdsql>=1.3.5; extra == 'all'
Requires-Dist: google-cloud-bigquery; extra == 'all'
Requires-Dist: hdbcli>=2.20.0; extra == 'all'
Requires-Dist: ibm-db>=3.2.0; extra == 'all'
Requires-Dist: libsql>=0.1.0; extra == 'all'
Requires-Dist: mariadb>=1.1.0; extra == 'all'
Requires-Dist: mssql-python>=1.1.0; extra == 'all'
Requires-Dist: oracledb>=2.0.0; extra == 'all'
Requires-Dist: paramiko<4.0.0,>=2.0.0; extra == 'all'
Requires-Dist: presto-python-client>=0.8.4; extra == 'all'
Requires-Dist: psycopg2-binary>=2.9.0; extra == 'all'
Requires-Dist: pyathena>=3.22.0; extra == 'all'
Requires-Dist: pymysql>=1.1.0; extra == 'all'
Requires-Dist: redshift-connector; extra == 'all'
Requires-Dist: requests>=2.32.4; extra == 'all'
Requires-Dist: snowflake-connector-python>=3.7.0; extra == 'all'
Requires-Dist: sshtunnel>=0.4.0; extra == 'all'
Requires-Dist: teradatasql>=20.0.0; extra == 'all'
Requires-Dist: trino>=0.329.0; extra == 'all'
Provides-Extra: athena
Requires-Dist: pyathena>=3.22.0; extra == 'athena'
Provides-Extra: bigquery
Requires-Dist: google-cloud-bigquery; extra == 'bigquery'
Provides-Extra: clickhouse
Requires-Dist: clickhouse-connect>=0.7.0; extra == 'clickhouse'
Provides-Extra: cockroachdb
Requires-Dist: psycopg2-binary>=2.9.0; extra == 'cockroachdb'
Provides-Extra: d1
Requires-Dist: requests>=2.32.4; extra == 'd1'
Provides-Extra: db2
Requires-Dist: ibm-db>=3.2.0; extra == 'db2'
Provides-Extra: duckdb
Requires-Dist: duckdb>=1.1.0; extra == 'duckdb'
Provides-Extra: firebird
Requires-Dist: firebirdsql>=1.3.5; extra == 'firebird'
Provides-Extra: flight
Requires-Dist: adbc-driver-flightsql>=1.0.0; extra == 'flight'
Provides-Extra: hana
Requires-Dist: hdbcli>=2.20.0; extra == 'hana'
Provides-Extra: mariadb
Requires-Dist: mariadb>=1.1.0; extra == 'mariadb'
Provides-Extra: mssql
Requires-Dist: mssql-python>=1.1.0; extra == 'mssql'
Provides-Extra: mysql
Requires-Dist: pymysql>=1.1.0; extra == 'mysql'
Provides-Extra: oracle
Requires-Dist: oracledb>=2.0.0; extra == 'oracle'
Provides-Extra: postgres
Requires-Dist: psycopg2-binary>=2.9.0; extra == 'postgres'
Provides-Extra: presto
Requires-Dist: presto-python-client>=0.8.4; extra == 'presto'
Provides-Extra: redshift
Requires-Dist: redshift-connector; extra == 'redshift'
Provides-Extra: snowflake
Requires-Dist: snowflake-connector-python>=3.7.0; extra == 'snowflake'
Provides-Extra: ssh
Requires-Dist: paramiko<4.0.0,>=2.0.0; extra == 'ssh'
Requires-Dist: sshtunnel>=0.4.0; extra == 'ssh'
Provides-Extra: teradata
Requires-Dist: teradatasql>=20.0.0; extra == 'teradata'
Provides-Extra: trino
Requires-Dist: trino>=0.329.0; extra == 'trino'
Provides-Extra: turso
Requires-Dist: libsql>=0.1.0; extra == 'turso'
